{
    "00425981": {
        "start": "00425981", 
        "successors": [
            "00425110", 
            "00425976", 
            "0042598d"
        ], 
        "end": "0042598c"
    }, 
    "00425971": {
        "start": "00425971", 
        "successors": [
            "00425976"
        ], 
        "end": "00425975"
    }, 
    "004258fd": {
        "start": "004258fd", 
        "successors": [
            "00425922"
        ], 
        "end": "00425908"
    }, 
    "0042592a": {
        "start": "0042592a", 
        "successors": [
            "00425931"
        ], 
        "end": "00425930"
    }, 
    "0042596a": {
        "start": "0042596a", 
        "successors": [
            "00425922", 
            "00425971"
        ], 
        "end": "00425970"
    }, 
    "004258e0": {
        "start": "004258e0", 
        "successors": [
            "00449078", 
            "00425971", 
            "004258fd"
        ], 
        "end": "004258fc"
    }, 
    "0042598d": {
        "start": "0042598d", 
        "successors": [
            "0042596a"
        ], 
        "end": "00425990"
    }, 
    "00425910": {
        "start": "00425910", 
        "successors": [
            "0042592a", 
            "00425914"
        ], 
        "end": "00425913"
    }, 
    "00425976": {
        "start": "00425976", 
        "successors": [], 
        "end": "00425980"
    }, 
    "00425931": {
        "start": "00425931", 
        "successors": [
            "00425931", 
            "00425947"
        ], 
        "end": "00425946"
    }, 
    "00425922": {
        "start": "00425922", 
        "successors": [
            "00425910", 
            "0042592a"
        ], 
        "end": "00425929"
    }, 
    "00425914": {
        "start": "00425914", 
        "successors": [
            "00425971", 
            "00425922"
        ], 
        "end": "00425921"
    }, 
    "00425947": {
        "start": "00425947", 
        "successors": [
            "00425981", 
            "00425968"
        ], 
        "end": "00425967"
    }, 
    "00425968": {
        "start": "00425968", 
        "successors": [
            "0042596a"
        ], 
        "end": "00425969"
    }
}