{
    "004183d0": {
        "start": "004183d0", 
        "successors": [
            "00449030", 
            "004490e0", 
            "00449160", 
            "00418438", 
            "00418422"
        ], 
        "end": "00418421"
    }, 
    "00418438": {
        "start": "00418438", 
        "successors": [], 
        "end": "00418440"
    }, 
    "00418422": {
        "start": "00418422", 
        "successors": [
            "00449158", 
            "00449190", 
            "00418438"
        ], 
        "end": "00418437"
    }
}