{
    "004417d0": {
        "start": "004417d0", 
        "successors": [
            "004417eb"
        ], 
        "end": "004417d9"
    }, 
    "004417e0": {
        "start": "004417e0", 
        "successors": [
            "004417ef", 
            "004417e9"
        ], 
        "end": "004417e8"
    }, 
    "004417e9": {
        "start": "004417e9", 
        "successors": [
            "004417eb"
        ], 
        "end": "004417ea"
    }, 
    "004417eb": {
        "start": "004417eb", 
        "successors": [
            "004417e0", 
            "004417ef"
        ], 
        "end": "004417ee"
    }, 
    "004417ef": {
        "start": "004417ef", 
        "successors": [], 
        "end": "004417f0"
    }
}