{
    "return_type": "undefined", 
    "address": "00407320", 
    "args": [
        {
            "type": "char *", 
            "name": "param_1"
        }
    ], 
    "calls": [
        "00449080", 
        "00433690", 
        "00422670", 
        "00433690", 
        "00406e50", 
        "00449140", 
        "00433690", 
        "00433690", 
        "00420a90", 
        "00449098", 
        "00433690", 
        "00433690", 
        "0041fd60", 
        "00433690", 
        "00433690", 
        "00420910", 
        "00433690", 
        "00420a90", 
        "00449098", 
        "00433690", 
        "00433690", 
        "00420a90", 
        "00449098", 
        "00449100", 
        "00433690", 
        "00449098", 
        "00433690"
    ], 
    "name": "FUN_00407320", 
    "stack_frame": 1108
}