{
    "00437abb": {
        "start": "00437abb", 
        "successors": [
            "00437ac1", 
            "00437abd"
        ], 
        "end": "00437abc"
    }, 
    "00437cfd": {
        "start": "00437cfd", 
        "successors": [
            "0043805d", 
            "00437d03"
        ], 
        "end": "00437d02"
    }, 
    "004380d7": {
        "start": "004380d7", 
        "successors": [
            "00437d03", 
            "004380dd"
        ], 
        "end": "004380dc"
    }, 
    "00437abd": {
        "start": "00437abd", 
        "successors": [
            "00437ac7", 
            "00437ac1"
        ], 
        "end": "00437ac0"
    }, 
    "004378c2": {
        "start": "004378c2", 
        "successors": [
            "004378cc"
        ], 
        "end": "004378cb"
    }, 
    "00437d03": {
        "start": "00437d03", 
        "successors": [
            "00437d30"
        ], 
        "end": "00437d2f"
    }, 
    "004378cc": {
        "start": "004378cc", 
        "successors": [
            "00440e20", 
            "00437aa5", 
            "00437a99"
        ], 
        "end": "00437a98"
    }, 
    "004372a0": {
        "start": "004372a0", 
        "successors": [
            "00437cf2", 
            "004373d1"
        ], 
        "end": "004373d0"
    }, 
    "004373e0": {
        "start": "004373e0", 
        "successors": [
            "00437610"
        ], 
        "end": "004375c9"
    }, 
    "0043805d": {
        "start": "0043805d", 
        "successors": [
            "00437b30", 
            "00438065"
        ], 
        "end": "00438064"
    }, 
    "004380ab": {
        "start": "004380ab", 
        "successors": [
            "004380cd", 
            "004380bd"
        ], 
        "end": "004380bc"
    }, 
    "004380cd": {
        "start": "004380cd", 
        "successors": [
            "004380a0", 
            "004380d7"
        ], 
        "end": "004380d6"
    }, 
    "00437b1d": {
        "start": "00437b1d", 
        "successors": [
            "00437cfd", 
            "00437b2d"
        ], 
        "end": "00437b2c"
    }, 
    "00437a9b": {
        "start": "00437a9b", 
        "successors": [
            "00437aa5", 
            "00437a9f"
        ], 
        "end": "00437a9e"
    }, 
    "00438052": {
        "start": "00438052", 
        "successors": [], 
        "end": "0043805c"
    }, 
    "004378a6": {
        "start": "004378a6", 
        "successors": [
            "004378cc", 
            "004378bc"
        ], 
        "end": "004378bb"
    }, 
    "00437a9f": {
        "start": "00437a9f", 
        "successors": [
            "00437aa5"
        ], 
        "end": "00437aa4"
    }, 
    "00437cf2": {
        "start": "00437cf2", 
        "successors": [], 
        "end": "00437cfc"
    }, 
    "00438077": {
        "start": "00438077", 
        "successors": [
            "004380a0"
        ], 
        "end": "0043809f"
    }, 
    "004373d1": {
        "start": "004373d1", 
        "successors": [
            "004373e0"
        ], 
        "end": "004373df"
    }, 
    "00437a99": {
        "start": "00437a99", 
        "successors": [
            "00437a9f", 
            "00437a9b"
        ], 
        "end": "00437a9a"
    }, 
    "004375d0": {
        "start": "004375d0", 
        "successors": [
            "00437610"
        ], 
        "end": "0043760f"
    }, 
    "00437d30": {
        "start": "00437d30", 
        "successors": [
            "00437d30", 
            "00438052"
        ], 
        "end": "00438051"
    }, 
    "0043789c": {
        "start": "0043789c", 
        "successors": [
            "004378a6"
        ], 
        "end": "004378a5"
    }, 
    "004378bc": {
        "start": "004378bc", 
        "successors": [
            "004378c2", 
            "004378be"
        ], 
        "end": "004378bd"
    }, 
    "004378be": {
        "start": "004378be", 
        "successors": [
            "004378cc", 
            "004378c2"
        ], 
        "end": "004378c1"
    }, 
    "00437b50": {
        "start": "00437b50", 
        "successors": [
            "00437b50", 
            "00437cf2"
        ], 
        "end": "00437cf1"
    }, 
    "0043806d": {
        "start": "0043806d", 
        "successors": [
            "00438077", 
            "0043806f"
        ], 
        "end": "0043806e"
    }, 
    "004380e3": {
        "start": "004380e3", 
        "successors": [
            "00437d03"
        ], 
        "end": "004380e7"
    }, 
    "004380a0": {
        "start": "004380a0", 
        "successors": [
            "00437cf2", 
            "004380ab"
        ], 
        "end": "004380aa"
    }, 
    "00437b30": {
        "start": "00437b30", 
        "successors": [
            "00437b50"
        ], 
        "end": "00437b4f"
    }, 
    "0043806f": {
        "start": "0043806f", 
        "successors": [
            "00437d03", 
            "00438077"
        ], 
        "end": "00438076"
    }, 
    "004380c3": {
        "start": "004380c3", 
        "successors": [
            "00437b30", 
            "004380cd"
        ], 
        "end": "004380cc"
    }, 
    "004380bd": {
        "start": "004380bd", 
        "successors": [
            "00437b30", 
            "004380c3"
        ], 
        "end": "004380c2"
    }, 
    "00437b2d": {
        "start": "00437b2d", 
        "successors": [
            "00437b30"
        ], 
        "end": "00437b2f"
    }, 
    "00437ac7": {
        "start": "00437ac7", 
        "successors": [
            "004375d0", 
            "00437ae2"
        ], 
        "end": "00437ae1"
    }, 
    "00437aa5": {
        "start": "00437aa5", 
        "successors": [
            "00437ac7", 
            "00437abb"
        ], 
        "end": "00437aba"
    }, 
    "00437896": {
        "start": "00437896", 
        "successors": [
            "0043789c", 
            "00437898"
        ], 
        "end": "00437897"
    }, 
    "00437610": {
        "start": "00437610", 
        "successors": [
            "00440e20", 
            "004378a6", 
            "00437896"
        ], 
        "end": "00437895"
    }, 
    "00437898": {
        "start": "00437898", 
        "successors": [
            "004378a6", 
            "0043789c"
        ], 
        "end": "0043789b"
    }, 
    "00437ae2": {
        "start": "00437ae2", 
        "successors": [
            "004373e0", 
            "00437b1d"
        ], 
        "end": "00437b1c"
    }, 
    "00438065": {
        "start": "00438065", 
        "successors": [
            "00437d03", 
            "0043806d"
        ], 
        "end": "0043806c"
    }, 
    "00437ac1": {
        "start": "00437ac1", 
        "successors": [
            "00437ac7"
        ], 
        "end": "00437ac6"
    }, 
    "004380dd": {
        "start": "004380dd", 
        "successors": [
            "004380a0", 
            "004380e3"
        ], 
        "end": "004380e2"
    }
}